kwonly_transformer/__init__.py
kwonly_transformer/main.py
tests/__init__.py
tests/test_transformer.py
kwonly_transformer-0.0.0.dist-info/LICENSE
kwonly_transformer-0.0.0.dist-info/METADATA
kwonly_transformer-0.0.0.dist-info/WHEEL
kwonly_transformer-0.0.0.dist-info/top_level.txt
kwonly_transformer-0.0.0.dist-info/RECORD
